{
  "Better On Bedrock": {
    "signal": "Friday, April 10, 2026",
    "version": "Friday, April 10, 2026",
    "tree_axe_relevant": null,
    "checked_at": "2026-06-21T16:49:54.396Z"
  },
  "RealismCraft": {
    "signal": "Tuesday, April 7, 2026",
    "version": "Tuesday, April 7, 2026",
    "tree_axe_relevant": null,
    "checked_at": "2026-06-21T16:49:54.812Z"
  },
  "Tinker's Construct": {
    "signal": "Tuesday, October 21, 2025",
    "version": "Tuesday, October 21, 2025",
    "tree_axe_relevant": null,
    "checked_at": "2026-06-21T16:49:55.058Z"
  },
  "Forest Craft": {
    "signal": "Thursday, April 9, 2026",
    "version": "Thursday, April 9, 2026",
    "tree_axe_relevant": null,
    "checked_at": "2026-06-21T16:49:55.519Z"
  },
  "Biomes Add-On": {
    "signal": "Tuesday, July 15, 2025",
    "version": "Tuesday, July 15, 2025",
    "tree_axe_relevant": null,
    "checked_at": "2026-06-21T16:49:55.748Z"
  },
  "Biomes + Structures Add-On": {
    "signal": "Monday, January 19, 2026",
    "version": "Monday, January 19, 2026",
    "tree_axe_relevant": null,
    "checked_at": "2026-06-21T16:49:55.990Z"
  },
  "Farming": {
    "signal": "Wednesday, August 20, 2025",
    "version": "Wednesday, August 20, 2025",
    "tree_axe_relevant": null,
    "checked_at": "2026-06-21T16:49:56.732Z"
  },
  "Biomes O' Plenty": {
    "signal": "Thursday, May 21, 2026",
    "version": "Thursday, May 21, 2026",
    "tree_axe_relevant": null,
    "checked_at": "2026-06-21T16:49:59.001Z"
  },
  "More Ores & Tools": {
    "signal": "Wednesday, November 13, 2024",
    "version": "Wednesday, November 13, 2024",
    "tree_axe_relevant": null,
    "checked_at": "2026-06-21T16:49:59.523Z"
  },
  "Nature": {
    "signal": "Tuesday, July 1, 2025",
    "version": "Tuesday, July 1, 2025",
    "tree_axe_relevant": null,
    "checked_at": "2026-06-21T16:49:59.942Z"
  }
}
